{
    "id": "213816",
    "first_name": "Jennifer",
    "last_name": "Esguerra",
    "data": {
        "profilePhoto": null,
        "job_title": "Merchandise Planner"
    },
    "last_login_timestamp": null,
    "created_timestamp": null,
    "modified_timestamp": "2018-11-29 23:20:52",
    "login_id": "1759121",
    "user_id": "213816",
    "role_id": "2",
    "status": "2",
    "fullName": "Jennifer Esguerra",
    "profile_picture": null,
    "titleTextEncoded": "jennifer-esguerra",
    "title": "Jennifer Esguerra",
    "videos_count": "0"
}