{
    "id": "213720",
    "first_name": "Aislynn",
    "last_name": "Ohaus",
    "data": {
        "profilePhoto": "\/api\/canvas\/logo\/151883341-0.3664497923571.jpg",
        "job_title": "Associate Buyer - Classic Handbags"
    },
    "last_login_timestamp": "1548254660",
    "created_timestamp": null,
    "modified_timestamp": "2018-11-01 15:46:29",
    "login_id": "1759121",
    "user_id": "213720",
    "role_id": "2",
    "status": "2",
    "fullName": "Aislynn Ohaus",
    "profile_picture": "\/api\/canvas\/logo\/151883341-0.3664497923571.jpg",
    "titleTextEncoded": "aislynn-ohaus",
    "title": "Aislynn Ohaus",
    "videos_count": "0"
}