{
    "id": "213976",
    "first_name": "Eric",
    "last_name": "Santiago",
    "data": {
        "profilePhoto": null,
        "job_title": "Admin EVP\/GBM Home & Beauty"
    },
    "last_login_timestamp": null,
    "created_timestamp": null,
    "modified_timestamp": "2019-02-07 15:23:17",
    "login_id": "1759121",
    "user_id": "213976",
    "role_id": "2",
    "status": "2",
    "fullName": "Eric Santiago",
    "profile_picture": null,
    "titleTextEncoded": "eric-santiago",
    "title": "Eric Santiago",
    "videos_count": "0"
}