{
    "id": "213843",
    "first_name": "Jennifer",
    "last_name": "Capuano",
    "data": {
        "profilePhoto": null,
        "job_title": "Buyer "
    },
    "last_login_timestamp": "1545294288",
    "created_timestamp": null,
    "modified_timestamp": "2018-12-06 23:21:09",
    "login_id": "1759121",
    "user_id": "213843",
    "role_id": "2",
    "status": "2",
    "fullName": "Jennifer Capuano",
    "profile_picture": null,
    "titleTextEncoded": "jennifer-capuano",
    "title": "Jennifer Capuano",
    "videos_count": "0"
}