{
    "title": "Party eyes all about shadow palette",
    "description": "@clinique Party eyes all about shadow palette! Must have and only $29.50 ??@stylecrewcentral #macysstylecrew #macysbeauty @clinique #makeupartist #makeupgoals ",
    "referenceId": null,
    "date_created": "1542122196",
    "date_modified": "1546466794",
    "tags": null,
    "status": "approved",
    "visibility": "1",
    "engagement_score": null,
    "conversion_score": null,
    "user_id": "213672",
    "id": "183347163",
    "loginId": "1759121",
    "entityType": "7",
    "titleTextEncoded": "party-eyes-all-about-shadow-palette",
    "linkUrl": null,
    "category": "Beauty",
    "tvp_profiles": null,
    "tvp_profiles_manual": null,
    "tvp_profiles_maxscore": null,
    "settings": null,
    "asset": {
        "sources": [
            {
                "width": 1024,
                "height": 1821,
                "format": "jpeg",
                "url": "https:\/\/s3-us-west-2.amazonaws.com\/video-dev.tvpage.com\/1759121\/183347163\/image-media--1024.jpeg?v=1542122200811"
            },
            {
                "width": 960,
                "height": 1707,
                "format": "jpeg",
                "url": "https:\/\/s3-us-west-2.amazonaws.com\/video-dev.tvpage.com\/1759121\/183347163\/image-media--960.jpeg?v=1542122200960"
            },
            {
                "width": 640,
                "height": 1138,
                "format": "jpeg",
                "url": "https:\/\/s3-us-west-2.amazonaws.com\/video-dev.tvpage.com\/1759121\/183347163\/image-media--640.jpeg?v=1542122200855"
            },
            {
                "width": 600,
                "height": 1066,
                "format": "jpeg",
                "url": "https:\/\/s3-us-west-2.amazonaws.com\/video-dev.tvpage.com\/1759121\/183347163\/image-media--600.jpeg?v=1542122200837"
            },
            {
                "width": 256,
                "height": 455,
                "format": "jpeg",
                "url": "https:\/\/s3-us-west-2.amazonaws.com\/video-dev.tvpage.com\/1759121\/183347163\/image-media--256.jpeg?v=1542122201173"
            }
        ],
        "thumbnails": [
            {
                "width": 640,
                "height": 360,
                "format": "jpeg",
                "url": "https:\/\/s3-us-west-2.amazonaws.com\/video-dev.tvpage.com\/1759121\/183347163\/image-thumbnail-640.jpeg?v=1542122201419"
            },
            {
                "width": 480,
                "height": 270,
                "format": "jpeg",
                "url": "https:\/\/s3-us-west-2.amazonaws.com\/video-dev.tvpage.com\/1759121\/183347163\/image-thumbnail-480.jpeg?v=1542122201408"
            },
            {
                "width": 256,
                "height": 144,
                "format": "jpeg",
                "url": "https:\/\/s3-us-west-2.amazonaws.com\/video-dev.tvpage.com\/1759121\/183347163\/image-thumbnail-256.jpeg?v=1542122201395"
            },
            {
                "width": 64,
                "height": 64,
                "format": "jpeg",
                "url": "https:\/\/s3-us-west-2.amazonaws.com\/video-dev.tvpage.com\/1759121\/183347163\/image-thumbnail-64.jpeg?v=1542122201391"
            }
        ],
        "thumbnailUrl": "https:\/\/s3-us-west-2.amazonaws.com\/video-dev.tvpage.com\/1759121\/183347163\/image-thumbnail-640.jpeg?v=1542122201419",
        "type": "photo"
    },
    "metrics_statistics": null,
    "tvp_enhanced_search": null,
    "tvp_enhanced_anti": null,
    "tvp_enhanced_brand": null,
    "PV_PI": null,
    "CPV_PI": null
}