{
    "title": "Go Red for Women #CalvinKleinRedDress",
    "description": "Macy’s is a national supporter of the #AmericanHeartAssociationsGoRedForWomen . And now through Feb.28,  Macy’s will donate 10% of the sale price from this Calvin Klein red dress to the #americanheartassociation \nSupport the cause in style! Shop the dress via the ??link in my bio . \n#macysstylecrew  #mylook  #Macys  @macys @goredforwomen #goredforwomen #macysgoredforwomen #macysgored #macysdresses #reddress #calvinklein  #macysstylecrew #stylecrewcentral #macysstylecrewtv ",
    "referenceId": null,
    "date_created": "1549342995",
    "date_modified": "1549344482",
    "tags": null,
    "status": "approved",
    "visibility": "1",
    "engagement_score": null,
    "conversion_score": null,
    "user_id": "213731",
    "id": "201538084",
    "loginId": "1759121",
    "entityType": "7",
    "titleTextEncoded": "go-red-for-women-calvinkleinreddress",
    "linkUrl": null,
    "category": "Women",
    "tvp_profiles": null,
    "tvp_profiles_manual": null,
    "tvp_profiles_maxscore": null,
    "settings": null,
    "asset": {
        "sources": [
            {
                "width": 1920,
                "height": 2560,
                "format": "jpeg",
                "url": "https:\/\/s3-us-west-2.amazonaws.com\/video-dev.tvpage.com\/1759121\/201538084\/image-media--1920.jpeg?v=1549343009459"
            },
            {
                "width": 1280,
                "height": 1706,
                "format": "jpeg",
                "url": "https:\/\/s3-us-west-2.amazonaws.com\/video-dev.tvpage.com\/1759121\/201538084\/image-media--1280.jpeg?v=1549343010105"
            },
            {
                "width": 1200,
                "height": 1600,
                "format": "jpeg",
                "url": "https:\/\/s3-us-west-2.amazonaws.com\/video-dev.tvpage.com\/1759121\/201538084\/image-media--1200.jpeg?v=1549343009082"
            },
            {
                "width": 1024,
                "height": 1365,
                "format": "jpeg",
                "url": "https:\/\/s3-us-west-2.amazonaws.com\/video-dev.tvpage.com\/1759121\/201538084\/image-media--1024.jpeg?v=1549343009981"
            },
            {
                "width": 1080,
                "height": 1440,
                "format": "jpeg",
                "url": "https:\/\/s3-us-west-2.amazonaws.com\/video-dev.tvpage.com\/1759121\/201538084\/image-media--1080.jpeg?v=1549343009182"
            },
            {
                "width": 960,
                "height": 1280,
                "format": "jpeg",
                "url": "https:\/\/s3-us-west-2.amazonaws.com\/video-dev.tvpage.com\/1759121\/201538084\/image-media--960.jpeg?v=1549343009780"
            },
            {
                "width": 640,
                "height": 853,
                "format": "jpeg",
                "url": "https:\/\/s3-us-west-2.amazonaws.com\/video-dev.tvpage.com\/1759121\/201538084\/image-media--640.jpeg?v=1549343009081"
            },
            {
                "width": 600,
                "height": 800,
                "format": "jpeg",
                "url": "https:\/\/s3-us-west-2.amazonaws.com\/video-dev.tvpage.com\/1759121\/201538084\/image-media--600.jpeg?v=1549343009490"
            },
            {
                "width": 256,
                "height": 341,
                "format": "jpeg",
                "url": "https:\/\/s3-us-west-2.amazonaws.com\/video-dev.tvpage.com\/1759121\/201538084\/image-media--256.jpeg?v=1549343009721"
            }
        ],
        "thumbnails": [
            {
                "width": 1920,
                "height": 1080,
                "format": "jpeg",
                "url": "https:\/\/s3-us-west-2.amazonaws.com\/video-dev.tvpage.com\/1759121\/201538084\/image-thumbnail-1920.jpeg?v=1549343010889"
            },
            {
                "width": 1280,
                "height": 720,
                "format": "jpeg",
                "url": "https:\/\/s3-us-west-2.amazonaws.com\/video-dev.tvpage.com\/1759121\/201538084\/image-thumbnail-1280.jpeg?v=1549343010811"
            },
            {
                "width": 640,
                "height": 360,
                "format": "jpeg",
                "url": "https:\/\/s3-us-west-2.amazonaws.com\/video-dev.tvpage.com\/1759121\/201538084\/image-thumbnail-640.jpeg?v=1549343010746"
            },
            {
                "width": 480,
                "height": 270,
                "format": "jpeg",
                "url": "https:\/\/s3-us-west-2.amazonaws.com\/video-dev.tvpage.com\/1759121\/201538084\/image-thumbnail-480.jpeg?v=1549343010709"
            },
            {
                "width": 256,
                "height": 144,
                "format": "jpeg",
                "url": "https:\/\/s3-us-west-2.amazonaws.com\/video-dev.tvpage.com\/1759121\/201538084\/image-thumbnail-256.jpeg?v=1549343010822"
            },
            {
                "width": 64,
                "height": 64,
                "format": "jpeg",
                "url": "https:\/\/s3-us-west-2.amazonaws.com\/video-dev.tvpage.com\/1759121\/201538084\/image-thumbnail-64.jpeg?v=1549343010904"
            }
        ],
        "thumbnailUrl": "https:\/\/s3-us-west-2.amazonaws.com\/video-dev.tvpage.com\/1759121\/201538084\/image-thumbnail-640.jpeg?v=1549343010746",
        "type": "photo"
    },
    "metrics_statistics": null,
    "tvp_enhanced_search": null,
    "tvp_enhanced_anti": null,
    "tvp_enhanced_brand": null,
    "PV_PI": null,
    "CPV_PI": null
}